zcmd/__init__.py
zcmd/handle.py
zcmd/zcmd.py
zcmd-0.0.6.dist-info/METADATA
zcmd-0.0.6.dist-info/WHEEL
zcmd-0.0.6.dist-info/top_level.txt
zcmd-0.0.6.dist-info/RECORD
