Metadata-Version: 2.1
Name: zcmd
Version: 0.0.6
Summary: A package use for jupyter notebook
Home-page: https://github.com/ouczbs/zcmd
Author: ouczbs
Author-email: ouczbs@qq.com
License: MIT
Platform: UNKNOWN
